{
  "Questions": {
    "2008": {
      "datasets": [
        {
          "data": [
            {
              "x": 0.3402777777777778,
              "y": 0.10416666666666667,
              "v": 144
            }
          ],
          "label": 0
        },
        {
          "data": [
            {
              "x": 0.2855018587360595,
              "y": 0.8131899451230308,
              "v": 2690
            }
          ],
          "label": 1
        },
        {
          "data": [
            {
              "x": 0.7969135802469136,
              "y": 5.380230849866323,
              "v": 8100
            }
          ],
          "label": 2
        },
        {
          "data": [
            {
              "x": 2.6833828219509512,
              "y": 22.09424572558061,
              "v": 9093
            }
          ],
          "label": 3
        },
        {
          "data": [
            {
              "x": 6.816666666666666,
              "y": 47.89453550464563,
              "v": 1680
            }
          ],
          "label": 4
        }
      ]
    },
    "2009": {
      "datasets": [
        {
          "data": [
            {
              "x": 0.10584539743239552,
              "y": 0.0025266320677410545,
              "v": 7322
            }
          ],
          "label": 0
        },
        {
          "data": [
            {
              "x": 0.3757562472599737,
              "y": 0.6002250000474466,
              "v": 22810
            }
          ],
          "label": 1
        },
        {
          "data": [
            {
              "x": 1.44898011810516,
              "y": 3.5730454892372108,
              "v": 38779
            }
          ],
          "label": 2
        },
        {
          "data": [
            {
              "x": 5.80377331055291,
              "y": 12.760619224795777,
              "v": 27509
            }
          ],
          "label": 3
        },
        {
          "data": [
            {
              "x": 17.001979078314957,
              "y": 23.43189828174425,
              "v": 3537
            }
          ],
          "label": 4
        }
      ]
    },
    "2010": {
      "datasets": [
        {
          "data": [
            {
              "x": 0.09046244020169805,
              "y": -0.0012160783806691663,
              "v": 46406
            }
          ],
          "label": 0
        },
        {
          "data": [
            {
              "x": 0.3556352281269878,
              "y": 0.5123358714330529,
              "v": 103758
            }
          ],
          "label": 1
        },
        {
          "data": [
            {
              "x": 1.9100453352421856,
              "y": 3.0917712316226993,
              "v": 96393
            }
          ],
          "label": 2
        },
        {
          "data": [
            {
              "x": 8.78523489932886,
              "y": 9.721931641875138,
              "v": 48276
            }
          ],
          "label": 3
        },
        {
          "data": [
            {
              "x": 26.19501647446458,
              "y": 18.32950129985956,
              "v": 4856
            }
          ],
          "label": 4
        }
      ]
    },
    "2011": {
      "datasets": [
        {
          "data": [
            {
              "x": 0.09345679012345678,
              "y": -0.008951780749014268,
              "v": 129600
            }
          ],
          "label": 0
        },
        {
          "data": [
            {
              "x": 0.39935086287268323,
              "y": 0.46665409388931794,
              "v": 258497
            }
          ],
          "label": 1
        },
        {
          "data": [
            {
              "x": 2.329665549934498,
              "y": 2.624797204681625,
              "v": 193123
            }
          ],
          "label": 2
        },
        {
          "data": [
            {
              "x": 11.511400292244494,
              "y": 7.983767976911689,
              "v": 72542
            }
          ],
          "label": 3
        },
        {
          "data": [
            {
              "x": 32.303454085930916,
              "y": 15.786433789919574,
              "v": 5935
            }
          ],
          "label": 4
        }
      ]
    },
    "2012": {
      "datasets": [
        {
          "data": [
            {
              "x": 0.051537660067892316,
              "y": -0.010833334805174125,
              "v": 446295
            }
          ],
          "label": 0
        },
        {
          "data": [
            {
              "x": 0.47407135281432455,
              "y": 0.44481036646366606,
              "v": 481803
            }
          ],
          "label": 1
        },
        {
          "data": [
            {
              "x": 2.7681922342457033,
              "y": 2.298113810639844,
              "v": 314200
            }
          ],
          "label": 2
        },
        {
          "data": [
            {
              "x": 13.803859422164726,
              "y": 7.063484715629445,
              "v": 92760
            }
          ],
          "label": 3
        },
        {
          "data": [
            {
              "x": 36.42330917874396,
              "y": 14.864095897572541,
              "v": 6624
            }
          ],
          "label": 4
        }
      ]
    },
    "2013": {
      "datasets": [
        {
          "data": [
            {
              "x": 0.043829379976495476,
              "y": -0.01475639873858799,
              "v": 1173391
            }
          ],
          "label": 0
        },
        {
          "data": [
            {
              "x": 0.581544831743799,
              "y": 0.41459794215634144,
              "v": 756406
            }
          ],
          "label": 1
        },
        {
          "data": [
            {
              "x": 3.1870822802583545,
              "y": 2.1158352922539967,
              "v": 427320
            }
          ],
          "label": 2
        },
        {
          "data": [
            {
              "x": 15.735435565697905,
              "y": 6.646954053677375,
              "v": 106046
            }
          ],
          "label": 3
        },
        {
          "data": [
            {
              "x": 39.687096311181286,
              "y": 14.38413006951475,
              "v": 6967
            }
          ],
          "label": 4
        }
      ]
    },
    "2014": {
      "datasets": [
        {
          "data": [
            {
              "x": 0.047673375886751454,
              "y": -0.019516016867974433,
              "v": 2002816
            }
          ],
          "label": 0
        },
        {
          "data": [
            {
              "x": 0.7011685375664275,
              "y": 0.384650211588406,
              "v": 1021790
            }
          ],
          "label": 1
        },
        {
          "data": [
            {
              "x": 3.645312306290599,
              "y": 1.9767193053261927,
              "v": 508171
            }
          ],
          "label": 2
        },
        {
          "data": [
            {
              "x": 17.470341989499076,
              "y": 6.368578881284187,
              "v": 112752
            }
          ],
          "label": 3
        },
        {
          "data": [
            {
              "x": 42.16760011201344,
              "y": 13.967279956228412,
              "v": 7142
            }
          ],
          "label": 4
        }
      ]
    },
    "2015": {
      "datasets": [
        {
          "data": [
            {
              "x": 0.04692538947858749,
              "y": -0.021302133601698924,
              "v": 2936811
            }
          ],
          "label": 0
        },
        {
          "data": [
            {
              "x": 0.7859907773888142,
              "y": 0.38181788417972784,
              "v": 1285753
            }
          ],
          "label": 1
        },
        {
          "data": [
            {
              "x": 4.108043411397689,
              "y": 1.9140497300105308,
              "v": 568975
            }
          ],
          "label": 2
        },
        {
          "data": [
            {
              "x": 19.034385699942504,
              "y": 6.193667229358263,
              "v": 116531
            }
          ],
          "label": 3
        },
        {
          "data": [
            {
              "x": 44.3308395677473,
              "y": 13.703431827097456,
              "v": 7218
            }
          ],
          "label": 4
        }
      ]
    },
    "2016": {
      "datasets": [
        {
          "data": [
            {
              "x": 0.04450115978565005,
              "y": -0.0212757793440649,
              "v": 4230092
            }
          ],
          "label": 0
        },
        {
          "data": [
            {
              "x": 0.8794332023737116,
              "y": 0.37791342229812,
              "v": 1520825
            }
          ],
          "label": 1
        },
        {
          "data": [
            {
              "x": 4.607003653174759,
              "y": 1.8586168362321012,
              "v": 605227
            }
          ],
          "label": 2
        },
        {
          "data": [
            {
              "x": 20.390973244656546,
              "y": 6.064442717217937,
              "v": 118182
            }
          ],
          "label": 3
        },
        {
          "data": [
            {
              "x": 46.10538674033149,
              "y": 13.478306672514442,
              "v": 7240
            }
          ],
          "label": 4
        }
      ]
    },
    "2017": {
      "datasets": [
        {
          "data": [
            {
              "x": 0.045040364258116784,
              "y": -0.022203663936722965,
              "v": 5240899
            }
          ],
          "label": 0
        },
        {
          "data": [
            {
              "x": 0.9665166029053632,
              "y": 0.379728748609998,
              "v": 1635527
            }
          ],
          "label": 1
        },
        {
          "data": [
            {
              "x": 4.930302660780918,
              "y": 1.8305035471943776,
              "v": 615045
            }
          ],
          "label": 2
        },
        {
          "data": [
            {
              "x": 21.0993163403106,
              "y": 5.99423475044116,
              "v": 118480
            }
          ],
          "label": 3
        },
        {
          "data": [
            {
              "x": 47.026657458563534,
              "y": 13.359945469470556,
              "v": 7240
            }
          ],
          "label": 4
        }
      ]
    }
  },
  "Answers": {
    "2008": {
      "datasets": [
        {
          "data": [
            {
              "x": 0.013888888888888888,
              "y": 0.006944444444444444,
              "v": 144
            }
          ],
          "label": 0
        },
        {
          "data": [
            {
              "x": 0.1613382899628253,
              "y": 0.14792441140024784,
              "v": 2690
            }
          ],
          "label": 1
        },
        {
          "data": [
            {
              "x": 0.4088888888888889,
              "y": 0.6406560356652945,
              "v": 8100
            }
          ],
          "label": 2
        },
        {
          "data": [
            {
              "x": 1.630155064335203,
              "y": 1.8134262102311995,
              "v": 9093
            }
          ],
          "label": 3
        },
        {
          "data": [
            {
              "x": 7.09702380952381,
              "y": 3.092388204746405,
              "v": 1680
            }
          ],
          "label": 4
        }
      ]
    },
    "2009": {
      "datasets": [
        {
          "data": [
            {
              "x": 0.15965583173996176,
              "y": -0.0003869616680324138,
              "v": 7322
            }
          ],
          "label": 0
        },
        {
          "data": [
            {
              "x": 0.22187637001315214,
              "y": 0.19225694661906853,
              "v": 22810
            }
          ],
          "label": 1
        },
        {
          "data": [
            {
              "x": 0.8052554217488848,
              "y": 0.7602745732888184,
              "v": 38779
            }
          ],
          "label": 2
        },
        {
          "data": [
            {
              "x": 4.471445708677161,
              "y": 1.8089713067142386,
              "v": 27509
            }
          ],
          "label": 3
        },
        {
          "data": [
            {
              "x": 33.99462821600226,
              "y": 3.0876864625334886,
              "v": 3537
            }
          ],
          "label": 4
        }
      ]
    },
    "2010": {
      "datasets": [
        {
          "data": [
            {
              "x": 0.1611645045899237,
              "y": -0.0050786801226880745,
              "v": 46406
            }
          ],
          "label": 0
        },
        {
          "data": [
            {
              "x": 0.21925056381194702,
              "y": 0.19727683648489758,
              "v": 103758
            }
          ],
          "label": 1
        },
        {
          "data": [
            {
              "x": 1.0051352276617598,
              "y": 0.8267284637066274,
              "v": 96393
            }
          ],
          "label": 2
        },
        {
          "data": [
            {
              "x": 7.259321401938852,
              "y": 1.8586522787314959,
              "v": 48276
            }
          ],
          "label": 3
        },
        {
          "data": [
            {
              "x": 73.40424217462933,
              "y": 3.0417267814068145,
              "v": 4856
            }
          ],
          "label": 4
        }
      ]
    },
    "2011": {
      "datasets": [
        {
          "data": [
            {
              "x": 0.11750771604938272,
              "y": -0.007913388355644476,
              "v": 129600
            }
          ],
          "label": 0
        },
        {
          "data": [
            {
              "x": 0.23919426531062257,
              "y": 0.22099346501999195,
              "v": 258497
            }
          ],
          "label": 1
        },
        {
          "data": [
            {
              "x": 1.2554641342564066,
              "y": 0.9118579834319038,
              "v": 193123
            }
          ],
          "label": 2
        },
        {
          "data": [
            {
              "x": 11.054409859116099,
              "y": 1.976335884000393,
              "v": 72542
            }
          ],
          "label": 3
        },
        {
          "data": [
            {
              "x": 123.53782645324347,
              "y": 3.0166253149269444,
              "v": 5935
            }
          ],
          "label": 4
        }
      ]
    },
    "2012": {
      "datasets": [
        {
          "data": [
            {
              "x": 0.062158437804591134,
              "y": -0.00597104973021428,
              "v": 446295
            }
          ],
          "label": 0
        },
        {
          "data": [
            {
              "x": 0.26713615315803346,
              "y": 0.24122382345957993,
              "v": 481803
            }
          ],
          "label": 1
        },
        {
          "data": [
            {
              "x": 1.6222692552514322,
              "y": 1.021028326320313,
              "v": 314200
            }
          ],
          "label": 2
        },
        {
          "data": [
            {
              "x": 15.57507546356188,
              "y": 2.099677471142662,
              "v": 92760
            }
          ],
          "label": 3
        },
        {
          "data": [
            {
              "x": 179.16847826086956,
              "y": 3.063195045250481,
              "v": 6624
            }
          ],
          "label": 4
        }
      ]
    },
    "2013": {
      "datasets": [
        {
          "data": [
            {
              "x": 0.05233038262608116,
              "y": -0.005082769365259187,
              "v": 1173391
            }
          ],
          "label": 0
        },
        {
          "data": [
            {
              "x": 0.3018127830821014,
              "y": 0.22224296523788337,
              "v": 756406
            }
          ],
          "label": 1
        },
        {
          "data": [
            {
              "x": 2.1361883366095666,
              "y": 1.0752368232832779,
              "v": 427320
            }
          ],
          "label": 2
        },
        {
          "data": [
            {
              "x": 21.021773569960207,
              "y": 2.1618048621454475,
              "v": 106046
            }
          ],
          "label": 3
        },
        {
          "data": [
            {
              "x": 243.43993110377494,
              "y": 2.9846893770432104,
              "v": 6967
            }
          ],
          "label": 4
        }
      ]
    },
    "2014": {
      "datasets": [
        {
          "data": [
            {
              "x": 0.05286107161117147,
              "y": -0.00544245942086047,
              "v": 2002816
            }
          ],
          "label": 0
        },
        {
          "data": [
            {
              "x": 0.3559234284931346,
              "y": 0.22068595486677145,
              "v": 1021790
            }
          ],
          "label": 1
        },
        {
          "data": [
            {
              "x": 2.7700518132675813,
              "y": 1.1312643890656664,
              "v": 508171
            }
          ],
          "label": 2
        },
        {
          "data": [
            {
              "x": 26.622578756917836,
              "y": 2.1550748900633008,
              "v": 112752
            }
          ],
          "label": 3
        },
        {
          "data": [
            {
              "x": 305.4145897507701,
              "y": 2.9281571717172166,
              "v": 7142
            }
          ],
          "label": 4
        }
      ]
    },
    "2015": {
      "datasets": [
        {
          "data": [
            {
              "x": 0.055017159769559565,
              "y": -0.006060907260351447,
              "v": 2936811
            }
          ],
          "label": 0
        },
        {
          "data": [
            {
              "x": 0.41823818416134356,
              "y": 0.2253705645771782,
              "v": 1285753
            }
          ],
          "label": 1
        },
        {
          "data": [
            {
              "x": 3.4694459334768664,
              "y": 1.1795803978076735,
              "v": 568975
            }
          ],
          "label": 2
        },
        {
          "data": [
            {
              "x": 32.394847722923515,
              "y": 2.1335342095267738,
              "v": 116531
            }
          ],
          "label": 3
        },
        {
          "data": [
            {
              "x": 362.1251039068994,
              "y": 2.88194588210459,
              "v": 7218
            }
          ],
          "label": 4
        }
      ]
    },
    "2016": {
      "datasets": [
        {
          "data": [
            {
              "x": 0.05647749505211707,
              "y": -0.0061890272445110275,
              "v": 4230092
            }
          ],
          "label": 0
        },
        {
          "data": [
            {
              "x": 0.49854190981868396,
              "y": 0.23432574992640917,
              "v": 1520825
            }
          ],
          "label": 1
        },
        {
          "data": [
            {
              "x": 4.305510163955012,
              "y": 1.2034313775894228,
              "v": 605227
            }
          ],
          "label": 2
        },
        {
          "data": [
            {
              "x": 38.21053121456736,
              "y": 2.08773071896874,
              "v": 118182
            }
          ],
          "label": 3
        },
        {
          "data": [
            {
              "x": 413.5966850828729,
              "y": 2.8289848770180974,
              "v": 7240
            }
          ],
          "label": 4
        }
      ]
    },
    "2017": {
      "datasets": [
        {
          "data": [
            {
              "x": 0.061409884067599854,
              "y": -0.006346745194891251,
              "v": 5240899
            }
          ],
          "label": 0
        },
        {
          "data": [
            {
              "x": 0.5847876555996936,
              "y": 0.2406397524910638,
              "v": 1635527
            }
          ],
          "label": 1
        },
        {
          "data": [
            {
              "x": 4.981604598037542,
              "y": 1.1856024869946882,
              "v": 615045
            }
          ],
          "label": 2
        },
        {
          "data": [
            {
              "x": 42.05286124240378,
              "y": 2.0377363568056834,
              "v": 118480
            }
          ],
          "label": 3
        },
        {
          "data": [
            {
              "x": 444.21436464088396,
              "y": 2.7914457567934314,
              "v": 7240
            }
          ],
          "label": 4
        }
      ]
    }
  }
}